flexible_dict/__init__.py
flexible_dict/flexible_dict.py
deepflex_dict-1.0.3.dist-info/METADATA
deepflex_dict-1.0.3.dist-info/WHEEL
deepflex_dict-1.0.3.dist-info/top_level.txt
deepflex_dict-1.0.3.dist-info/RECORD
