Metadata-Version: 2.4
Name: deepflex-dict
Version: 1.0.3
Summary: A dictionary with flexible options
Home-page: https://github.com/ehsankarbasian/flexible_dict
Author: Ehsan Karbasian
Author-email: ehsan.karbasian@gmail.com
Classifier: Programming Language :: Python :: 3
Classifier: License :: OSI Approved :: MIT License
Classifier: Operating System :: OS Independent
Requires-Python: >=3.6
Dynamic: author
Dynamic: author-email
Dynamic: classifier
Dynamic: description
Dynamic: description-content-type
Dynamic: home-page
Dynamic: requires-python
Dynamic: summary
